{
  "dialect": "sqlite",
  "id": "ac49e61a-1eb3-4963-994e-2869e2195c33",
  "prevIds": [
    "3f1a6b75-0f14-4802-b39d-d44d3bfd9f25"
  ],
  "version": "7",
  "ddl": [
    {
      "name": "accounts",
      "entityType": "tables"
    },
    {
      "type": "integer",
      "notNull": true,
      "autoincrement": false,
      "default": null,
      "generated": null,
      "name": "created_at",
      "table": "accounts",
      "entityType": "columns"
    },
    {
      "type": "integer",
      "notNull": true,
      "autoincrement": false,
      "default": null,
      "generated": null,
      "name": "updated_at",
      "table": "accounts",
      "entityType": "columns"
    },
    {
      "type": "integer",
      "notNull": false,
      "autoincrement": true,
      "default": null,
      "generated": null,
      "name": "id",
      "table": "accounts",
      "entityType": "columns"
    },
    {
      "columns": [
        "id"
      ],
      "nameExplicit": false,
      "name": "accounts_pk",
      "table": "accounts",
      "entityType": "pks"
    },
    {
      "type": "integer",
      "notNull": true,
      "autoincrement": false,
      "default": null,
      "generated": null,
      "name": "account_id",
      "table": "accounts",
      "entityType": "columns"
    },
    {
      "type": "text",
      "notNull": true,
      "autoincrement": false,
      "default": null,
      "generated": null,
      "name": "provider_id",
      "table": "accounts",
      "entityType": "columns"
    },
    {
      "type": "integer",
      "notNull": true,
      "autoincrement": false,
      "default": null,
      "generated": null,
      "name": "user_id",
      "table": "accounts",
      "entityType": "columns"
    },
    {
      "type": "text",
      "notNull": false,
      "autoincrement": false,
      "default": null,
      "generated": null,
      "name": "access_token",
      "table": "accounts",
      "entityType": "columns"
    },
    {
      "type": "text",
      "notNull": false,
      "autoincrement": false,
      "default": null,
      "generated": null,
      "name": "refresh_token",
      "table": "accounts",
      "entityType": "columns"
    },
    {
      "type": "text",
      "notNull": false,
      "autoincrement": false,
      "default": null,
      "generated": null,
      "name": "id_token",
      "table": "accounts",
      "entityType": "columns"
    },
    {
      "type": "integer",
      "notNull": false,
      "autoincrement": false,
      "default": null,
      "generated": null,
      "name": "access_token_expires_at",
      "table": "accounts",
      "entityType": "columns"
    },
    {
      "type": "integer",
      "notNull": false,
      "autoincrement": false,
      "default": null,
      "generated": null,
      "name": "refresh_token_expires_at",
      "table": "accounts",
      "entityType": "columns"
    },
    {
      "type": "text",
      "notNull": false,
      "autoincrement": false,
      "default": null,
      "generated": null,
      "name": "scope",
      "table": "accounts",
      "entityType": "columns"
    },
    {
      "type": "text",
      "notNull": false,
      "autoincrement": false,
      "default": null,
      "generated": null,
      "name": "password",
      "table": "accounts",
      "entityType": "columns"
    },
    {
      "columns": [
        "user_id"
      ],
      "tableTo": "users",
      "columnsTo": [
        "id"
      ],
      "onUpdate": "NO ACTION",
      "onDelete": "CASCADE",
      "nameExplicit": false,
      "name": "accounts_user_id_users_id_fk",
      "table": "accounts",
      "entityType": "fks"
    },
    {
      "name": "sessions",
      "entityType": "tables"
    },
    {
      "type": "integer",
      "notNull": true,
      "autoincrement": false,
      "default": null,
      "generated": null,
      "name": "created_at",
      "table": "sessions",
      "entityType": "columns"
    },
    {
      "type": "integer",
      "notNull": true,
      "autoincrement": false,
      "default": null,
      "generated": null,
      "name": "updated_at",
      "table": "sessions",
      "entityType": "columns"
    },
    {
      "type": "integer",
      "notNull": false,
      "autoincrement": true,
      "default": null,
      "generated": null,
      "name": "id",
      "table": "sessions",
      "entityType": "columns"
    },
    {
      "columns": [
        "id"
      ],
      "nameExplicit": false,
      "name": "sessions_pk",
      "table": "sessions",
      "entityType": "pks"
    },
    {
      "type": "integer",
      "notNull": true,
      "autoincrement": false,
      "default": null,
      "generated": null,
      "name": "user_id",
      "table": "sessions",
      "entityType": "columns"
    },
    {
      "type": "integer",
      "notNull": true,
      "autoincrement": false,
      "default": null,
      "generated": null,
      "name": "expires_at",
      "table": "sessions",
      "entityType": "columns"
    },
    {
      "type": "text",
      "notNull": true,
      "autoincrement": false,
      "default": null,
      "generated": null,
      "name": "token",
      "table": "sessions",
      "entityType": "columns"
    },
    {
      "type": "text",
      "notNull": false,
      "autoincrement": false,
      "default": null,
      "generated": null,
      "name": "user_agent",
      "table": "sessions",
      "entityType": "columns"
    },
    {
      "columns": [
        {
          "value": "token",
          "isExpression": false
        }
      ],
      "isUnique": true,
      "where": null,
      "origin": "manual",
      "name": "sessions_token_unique",
      "table": "sessions",
      "entityType": "indexes"
    },
    {
      "columns": [
        "user_id"
      ],
      "tableTo": "users",
      "columnsTo": [
        "id"
      ],
      "onUpdate": "NO ACTION",
      "onDelete": "CASCADE",
      "nameExplicit": false,
      "name": "sessions_user_id_users_id_fk",
      "table": "sessions",
      "entityType": "fks"
    },
    {
      "name": "users",
      "entityType": "tables"
    },
    {
      "type": "integer",
      "notNull": true,
      "autoincrement": false,
      "default": null,
      "generated": null,
      "name": "created_at",
      "table": "users",
      "entityType": "columns"
    },
    {
      "type": "integer",
      "notNull": true,
      "autoincrement": false,
      "default": null,
      "generated": null,
      "name": "updated_at",
      "table": "users",
      "entityType": "columns"
    },
    {
      "type": "integer",
      "notNull": false,
      "autoincrement": true,
      "default": null,
      "generated": null,
      "name": "id",
      "table": "users",
      "entityType": "columns"
    },
    {
      "columns": [
        "id"
      ],
      "nameExplicit": false,
      "name": "users_pk",
      "table": "users",
      "entityType": "pks"
    },
    {
      "type": "text",
      "notNull": true,
      "autoincrement": false,
      "default": null,
      "generated": null,
      "name": "name",
      "table": "users",
      "entityType": "columns"
    },
    {
      "type": "text",
      "notNull": true,
      "autoincrement": false,
      "default": null,
      "generated": null,
      "name": "email",
      "table": "users",
      "entityType": "columns"
    },
    {
      "type": "integer",
      "notNull": true,
      "autoincrement": false,
      "default": null,
      "generated": null,
      "name": "email_verified",
      "table": "users",
      "entityType": "columns"
    },
    {
      "type": "text",
      "notNull": false,
      "autoincrement": false,
      "default": null,
      "generated": null,
      "name": "image",
      "table": "users",
      "entityType": "columns"
    },
    {
      "columns": [
        {
          "value": "email",
          "isExpression": false
        }
      ],
      "isUnique": true,
      "where": null,
      "origin": "manual",
      "name": "users_email_unique",
      "table": "users",
      "entityType": "indexes"
    },
    {
      "name": "verifications",
      "entityType": "tables"
    },
    {
      "type": "integer",
      "notNull": true,
      "autoincrement": false,
      "default": null,
      "generated": null,
      "name": "created_at",
      "table": "verifications",
      "entityType": "columns"
    },
    {
      "type": "integer",
      "notNull": true,
      "autoincrement": false,
      "default": null,
      "generated": null,
      "name": "updated_at",
      "table": "verifications",
      "entityType": "columns"
    },
    {
      "type": "integer",
      "notNull": false,
      "autoincrement": true,
      "default": null,
      "generated": null,
      "name": "id",
      "table": "verifications",
      "entityType": "columns"
    },
    {
      "columns": [
        "id"
      ],
      "nameExplicit": false,
      "name": "verifications_pk",
      "table": "verifications",
      "entityType": "pks"
    },
    {
      "type": "text",
      "notNull": true,
      "autoincrement": false,
      "default": null,
      "generated": null,
      "name": "identifier",
      "table": "verifications",
      "entityType": "columns"
    },
    {
      "type": "text",
      "notNull": true,
      "autoincrement": false,
      "default": null,
      "generated": null,
      "name": "value",
      "table": "verifications",
      "entityType": "columns"
    },
    {
      "type": "integer",
      "notNull": true,
      "autoincrement": false,
      "default": null,
      "generated": null,
      "name": "expires_at",
      "table": "verifications",
      "entityType": "columns"
    },
    {
      "name": "chats",
      "entityType": "tables"
    },
    {
      "type": "integer",
      "notNull": false,
      "autoincrement": false,
      "default": null,
      "generated": null,
      "name": "id",
      "table": "chats",
      "entityType": "columns"
    },
    {
      "columns": [
        "id"
      ],
      "nameExplicit": false,
      "name": "chats_pk",
      "table": "chats",
      "entityType": "pks"
    },
    {
      "type": "integer",
      "notNull": true,
      "autoincrement": false,
      "default": null,
      "generated": null,
      "name": "created_at",
      "table": "chats",
      "entityType": "columns"
    },
    {
      "type": "integer",
      "notNull": true,
      "autoincrement": false,
      "default": null,
      "generated": null,
      "name": "updated_at",
      "table": "chats",
      "entityType": "columns"
    },
    {
      "type": "text",
      "notNull": true,
      "autoincrement": false,
      "default": null,
      "generated": null,
      "name": "slug",
      "table": "chats",
      "entityType": "columns"
    },
    {
      "type": "integer",
      "notNull": true,
      "autoincrement": false,
      "default": null,
      "generated": null,
      "name": "user_id",
      "table": "chats",
      "entityType": "columns"
    },
    {
      "type": "text",
      "notNull": false,
      "autoincrement": false,
      "default": "''",
      "generated": null,
      "name": "title",
      "table": "chats",
      "entityType": "columns"
    },
    {
      "type": "integer",
      "notNull": false,
      "autoincrement": false,
      "default": null,
      "generated": null,
      "name": "shared",
      "table": "chats",
      "entityType": "columns"
    },
    {
      "columns": [
        {
          "value": "slug",
          "isExpression": false
        }
      ],
      "isUnique": true,
      "where": null,
      "origin": "manual",
      "name": "chats_slug_unique",
      "table": "chats",
      "entityType": "indexes"
    },
    {
      "columns": [
        {
          "value": "id",
          "isExpression": false
        },
        {
          "value": "user_id",
          "isExpression": false
        }
      ],
      "isUnique": true,
      "where": null,
      "origin": "manual",
      "name": "uq_chat_user",
      "table": "chats",
      "entityType": "indexes"
    },
    {
      "columns": [
        {
          "value": "id",
          "isExpression": false
        },
        {
          "value": "slug",
          "isExpression": false
        }
      ],
      "isUnique": true,
      "where": null,
      "origin": "manual",
      "name": "uq_chat_slug",
      "table": "chats",
      "entityType": "indexes"
    },
    {
      "columns": [
        "user_id"
      ],
      "tableTo": "users",
      "columnsTo": [
        "id"
      ],
      "onUpdate": "NO ACTION",
      "onDelete": "CASCADE",
      "nameExplicit": false,
      "name": "chats_user_id_users_id_fk",
      "table": "chats",
      "entityType": "fks"
    },
    {
      "name": "messages",
      "entityType": "tables"
    },
    {
      "type": "integer",
      "notNull": false,
      "autoincrement": false,
      "default": null,
      "generated": null,
      "name": "id",
      "table": "messages",
      "entityType": "columns"
    },
    {
      "columns": [
        "id"
      ],
      "nameExplicit": false,
      "name": "messages_pk",
      "table": "messages",
      "entityType": "pks"
    },
    {
      "type": "integer",
      "notNull": true,
      "autoincrement": false,
      "default": null,
      "generated": null,
      "name": "created_at",
      "table": "messages",
      "entityType": "columns"
    },
    {
      "type": "integer",
      "notNull": true,
      "autoincrement": false,
      "default": null,
      "generated": null,
      "name": "updated_at",
      "table": "messages",
      "entityType": "columns"
    },
    {
      "type": "integer",
      "notNull": true,
      "autoincrement": false,
      "default": null,
      "generated": null,
      "name": "chat_id",
      "table": "messages",
      "entityType": "columns"
    },
    {
      "type": "text",
      "notNull": true,
      "autoincrement": false,
      "default": null,
      "generated": null,
      "name": "role",
      "table": "messages",
      "entityType": "columns"
    },
    {
      "type": "text",
      "notNull": true,
      "autoincrement": false,
      "default": "'[]'",
      "generated": null,
      "name": "parts",
      "table": "messages",
      "entityType": "columns"
    },
    {
      "type": "text",
      "notNull": true,
      "autoincrement": false,
      "default": "'[]'",
      "generated": null,
      "name": "tools",
      "table": "messages",
      "entityType": "columns"
    },
    {
      "type": "integer",
      "notNull": false,
      "autoincrement": false,
      "default": "false",
      "generated": null,
      "name": "reasoning",
      "table": "messages",
      "entityType": "columns"
    },
    {
      "columns": [
        {
          "value": "id",
          "isExpression": false
        },
        {
          "value": "chat_id",
          "isExpression": false
        }
      ],
      "isUnique": true,
      "where": null,
      "origin": "manual",
      "name": "uq_message_chat",
      "table": "messages",
      "entityType": "indexes"
    },
    {
      "columns": [
        "chat_id"
      ],
      "tableTo": "chats",
      "columnsTo": [
        "id"
      ],
      "onUpdate": "NO ACTION",
      "onDelete": "CASCADE",
      "nameExplicit": false,
      "name": "messages_chat_id_chats_id_fk",
      "table": "messages",
      "entityType": "fks"
    },
    {
      "name": "keys",
      "entityType": "tables"
    },
    {
      "type": "integer",
      "notNull": false,
      "autoincrement": false,
      "default": null,
      "generated": null,
      "name": "id",
      "table": "keys",
      "entityType": "columns"
    },
    {
      "columns": [
        "id"
      ],
      "nameExplicit": false,
      "name": "keys_pk",
      "table": "keys",
      "entityType": "pks"
    },
    {
      "type": "integer",
      "notNull": true,
      "autoincrement": false,
      "default": null,
      "generated": null,
      "name": "created_at",
      "table": "keys",
      "entityType": "columns"
    },
    {
      "type": "integer",
      "notNull": true,
      "autoincrement": false,
      "default": null,
      "generated": null,
      "name": "updated_at",
      "table": "keys",
      "entityType": "columns"
    },
    {
      "type": "integer",
      "notNull": true,
      "autoincrement": false,
      "default": null,
      "generated": null,
      "name": "user_id",
      "table": "keys",
      "entityType": "columns"
    },
    {
      "type": "text",
      "notNull": true,
      "autoincrement": false,
      "default": null,
      "generated": null,
      "name": "provider",
      "table": "keys",
      "entityType": "columns"
    },
    {
      "type": "text",
      "notNull": true,
      "autoincrement": false,
      "default": null,
      "generated": null,
      "name": "api_key",
      "table": "keys",
      "entityType": "columns"
    },
    {
      "columns": [
        {
          "value": "id",
          "isExpression": false
        },
        {
          "value": "user_id",
          "isExpression": false
        }
      ],
      "isUnique": true,
      "where": null,
      "origin": "manual",
      "name": "uq_key_user",
      "table": "keys",
      "entityType": "indexes"
    },
    {
      "columns": [
        {
          "value": "user_id",
          "isExpression": false
        },
        {
          "value": "provider",
          "isExpression": false
        }
      ],
      "isUnique": true,
      "where": null,
      "origin": "manual",
      "name": "uq_key_user_provider",
      "table": "keys",
      "entityType": "indexes"
    },
    {
      "columns": [
        "user_id"
      ],
      "tableTo": "users",
      "columnsTo": [
        "id"
      ],
      "onUpdate": "NO ACTION",
      "onDelete": "CASCADE",
      "nameExplicit": false,
      "name": "keys_user_id_users_id_fk",
      "table": "keys",
      "entityType": "fks"
    },
    {
      "name": "files",
      "entityType": "tables"
    },
    {
      "type": "integer",
      "notNull": false,
      "autoincrement": false,
      "default": null,
      "generated": null,
      "name": "id",
      "table": "files",
      "entityType": "columns"
    },
    {
      "columns": [
        "id"
      ],
      "nameExplicit": false,
      "name": "files_pk",
      "table": "files",
      "entityType": "pks"
    },
    {
      "type": "integer",
      "notNull": true,
      "autoincrement": false,
      "default": null,
      "generated": null,
      "name": "created_at",
      "table": "files",
      "entityType": "columns"
    },
    {
      "type": "integer",
      "notNull": true,
      "autoincrement": false,
      "default": null,
      "generated": null,
      "name": "updated_at",
      "table": "files",
      "entityType": "columns"
    },
    {
      "type": "integer",
      "notNull": true,
      "autoincrement": false,
      "default": null,
      "generated": null,
      "name": "user_id",
      "table": "files",
      "entityType": "columns"
    },
    {
      "type": "text",
      "notNull": true,
      "autoincrement": false,
      "default": null,
      "generated": null,
      "name": "storage_key",
      "table": "files",
      "entityType": "columns"
    },
    {
      "type": "text",
      "notNull": true,
      "autoincrement": false,
      "default": null,
      "generated": null,
      "name": "name",
      "table": "files",
      "entityType": "columns"
    },
    {
      "type": "integer",
      "notNull": true,
      "autoincrement": false,
      "default": null,
      "generated": null,
      "name": "size",
      "table": "files",
      "entityType": "columns"
    },
    {
      "type": "text",
      "notNull": true,
      "autoincrement": false,
      "default": null,
      "generated": null,
      "name": "type",
      "table": "files",
      "entityType": "columns"
    },
    {
      "columns": [
        {
          "value": "storage_key",
          "isExpression": false
        }
      ],
      "isUnique": true,
      "where": null,
      "origin": "manual",
      "name": "files_storageKey_unique",
      "table": "files",
      "entityType": "indexes"
    },
    {
      "columns": [
        {
          "value": "id",
          "isExpression": false
        },
        {
          "value": "user_id",
          "isExpression": false
        }
      ],
      "isUnique": true,
      "where": null,
      "origin": "manual",
      "name": "uq_file_user",
      "table": "files",
      "entityType": "indexes"
    },
    {
      "columns": [
        {
          "value": "storage_key",
          "isExpression": false
        }
      ],
      "isUnique": true,
      "where": null,
      "origin": "manual",
      "name": "uq_file_storageKey",
      "table": "files",
      "entityType": "indexes"
    },
    {
      "columns": [
        "user_id"
      ],
      "tableTo": "users",
      "columnsTo": [
        "id"
      ],
      "onUpdate": "NO ACTION",
      "onDelete": "CASCADE",
      "nameExplicit": false,
      "name": "files_user_id_users_id_fk",
      "table": "files",
      "entityType": "fks"
    },
    {
      "name": "storages",
      "entityType": "tables"
    },
    {
      "type": "integer",
      "notNull": false,
      "autoincrement": false,
      "default": null,
      "generated": null,
      "name": "id",
      "table": "storages",
      "entityType": "columns"
    },
    {
      "columns": [
        "id"
      ],
      "nameExplicit": false,
      "name": "storages_pk",
      "table": "storages",
      "entityType": "pks"
    },
    {
      "type": "integer",
      "notNull": true,
      "autoincrement": false,
      "default": null,
      "generated": null,
      "name": "created_at",
      "table": "storages",
      "entityType": "columns"
    },
    {
      "type": "integer",
      "notNull": true,
      "autoincrement": false,
      "default": null,
      "generated": null,
      "name": "updated_at",
      "table": "storages",
      "entityType": "columns"
    },
    {
      "type": "integer",
      "notNull": true,
      "autoincrement": false,
      "default": null,
      "generated": null,
      "name": "user_id",
      "table": "storages",
      "entityType": "columns"
    },
    {
      "type": "integer",
      "notNull": true,
      "autoincrement": false,
      "default": "20971520",
      "generated": null,
      "name": "storage",
      "table": "storages",
      "entityType": "columns"
    },
    {
      "columns": [
        {
          "value": "id",
          "isExpression": false
        },
        {
          "value": "user_id",
          "isExpression": false
        }
      ],
      "isUnique": true,
      "where": null,
      "origin": "manual",
      "name": "uq_storage_user",
      "table": "storages",
      "entityType": "indexes"
    },
    {
      "columns": [
        "user_id"
      ],
      "tableTo": "users",
      "columnsTo": [
        "id"
      ],
      "onUpdate": "NO ACTION",
      "onDelete": "CASCADE",
      "nameExplicit": false,
      "name": "storages_user_id_users_id_fk",
      "table": "storages",
      "entityType": "fks"
    }
  ],
  "renames": [
    "\"files\".\"r2_key\"->\"files\".\"storage_key\""
  ]
}